pysession.py
setup.cfg
setup.py
pysession.egg-info/PKG-INFO
pysession.egg-info/SOURCES.txt
pysession.egg-info/dependency_links.txt
pysession.egg-info/pbr.json
pysession.egg-info/top_level.txt