Metadata-Version: 1.1
Name: pysession
Version: 0.1.2
Summary: Automatically save python interpreter session code to a file or secret Gist
Home-page: https://github.com/FallibleInc/pysession
Author: Fallible
Author-email: hello@fallible.co
License: UNKNOWN
Download-URL: https://github.com/FallibleInc/pysession/tarball/0.1.2
Platform: UNKNOWN
Classifier: Development Status :: 5 - Production/Stable
Classifier: Intended Audience :: Developers
Classifier: Intended Audience :: Science/Research
Classifier: License :: OSI Approved :: MIT License
Classifier: Operating System :: OS Independent
Classifier: Framework :: IPython
Classifier: Framework :: IDLE
Classifier: Programming Language :: Python
Classifier: Programming Language :: Python :: 2
Classifier: Programming Language :: Python :: 2.6
Classifier: Programming Language :: Python :: 2.7
Classifier: Programming Language :: Python :: 3
Classifier: Programming Language :: Python :: 3.2
Classifier: Programming Language :: Python :: 3.3
Classifier: Programming Language :: Python :: 3.4
Classifier: Programming Language :: Python :: 3.5
Classifier: Programming Language :: Python :: Implementation :: PyPy
Classifier: Topic :: Utilities
